[
    {
      "id": 1,
      "question": "1 + 1",
      "level": 1,
      "category": "addition"
    },
    {
      "id": 2,
      "question": "2 + 3",
      "level": 1,
      "category": "addition"
    },
    {
      "id": 3,
      "question": "4 + 5",
      "level": 1,
      "category": "addition"
    },
    {
      "id": 4,
      "question": "3 + 6",
      "level": 1,
      "category": "addition"
    },
    {
      "id": 5,
      "question": "1 + 8",
      "level": 1,
      "category": "addition"
    },
    {
      "id": 6,
      "question": "9 + 0",
      "level": 1,
      "category": "addition"
    },
    {
      "id": 7,
      "question": "7 + 2",
      "level": 1,
      "category": "addition"
    },
    {
      "id": 8,
      "question": "3 + 5",
      "level": 1,
      "category": "addition"
    },
    {
      "id": 9,
      "question": "6 + 2",
      "level": 1,
      "category": "addition"
    },
    {
      "id": 10,
      "question": "4 + 4",
      "level": 1,
      "category": "addition"
    },
    {
      "id": 11,
      "question": "2 + 8",
      "level": 1,
      "category": "addition"
    },
    {
      "id": 12,
      "question": "7 + 1",
      "level": 1,
      "category": "addition"
    },
    {
      "id": 13,
      "question": "5 + 3",
      "level": 1,
      "category": "addition"
    }
  ]